{
  "player": {
    "klass": "Player",
    "req_params": 0,
    "@id": 1360,
    "@name": "Player",
    "@level": 1,
    "@xp": 0,
    "@health": 100,
    "@max_health": 100,
    "@mana": 100,
    "@max_mana": 100,
    "@base_damage": "1..5",
    "@damage": "10..15",
    "@armor": 1,
    "@pos_x": 0,
    "@pos_y": 0,
    "@dead": false,
    "@unfinished_quests": [],
    "@finished_quests": [],
    "@inventory": "REF1380",
    "@equipped_weapon": "REF1140",
    "@abilities": ["REF1240", "REF1260"],
    "@interacting_with": null,
    "@map_marker": "#",
    "@image": "                                   ..=*#.\n                                  -*#%%%*++:\n                                  #####%#%#*-.\n                                 +#%%%%%%%%%#%\n                                =#%%%#+*#%@%%%\n                                +%+::....-+%%@=\n                                =-:.......:+%@#.\n                                +::.......:=#@#.\n                     .........  =:........:+*%%-\n                    ...:==.:=-.:+=-:-=**+--=*#%:\n                    ...-+--:+**%%%%#+@@%*+#***#.\n                   :...::--:..=%@@#.=@@@%=++**%.\n                  .......:-.:.=+%%+.-###+.:-*-+.\n                ............   #*+...---...:-...\n               ..........::     =-=::.....::.-..\n              ::......:::.      ---.......:::..\n             ::.....:-:.        -::::.....::..\n            ::.....:.           :+=::=....:-=\n           ::.....::            :=--......:=:\n         .::.....:.             :=:....:::=-:\n        :::.....::               =:..::::==.:\n       :::....::.                ========-:.:\n      :-:.....::                  +=+++=::..-\n     :-::...:::.                  ++++-::...-\n     -::.....::                   +++=::....-\n    --::....::                    -=--:....::-\n   --:::..:::.                    .-:::.....::.\n  =-::::::::-:.                   --:::.......::\n :--:::::::-=::...   ..         .:=-:..............\n =--:::::-==:.....:::::....   ..:---:.............. .\n.=-------==-::....:::..:...     :::::.............     :.\n==:------:-:::::::::::::..      :................      :::::\n.+------::-:::::::-----:..      ................      ..::::\n =+----::-:::---------+-:.      ...............       .....:\n  =+-:::--::::--===---=+:        ..............       .....:\n   .+++===---::--====++#-         ............        ..::.:\n     .-++==------==+***#+.        ..........          .:::::\n       .-+++==--=++****#*..        .......          . ::::::\n          ==+++++++***+**:...         ..            . :---::\n            .:::::.:=*++*:....  .                   . -==---\n                     *++*::.... ..                ....=*+===\n                     :*+*-:...........................=%#*++\n                      +++-::::......................::*%%#*+\n                      :*+-::::.....................::-#%%#++\n                       ++-::::::.................::::=##%#+-\n                       -+--:::::.................::::=**##+=\n                        +--:::::..............::::::-=**#:-+\n",
    "@gold": 100
  },
  "npcs": [
    {
      "klass": "Enemy",
      "req_params": 4,
      "@id": 1420,
      "@name": "Lopov",
      "@pos_x": 6,
      "@pos_y": 6,
      "@map_marker": "@",
      "@image": "                              -++++=\n                         :+#*********#:\n                        =#####**##*****+\n           .           =#%####**#*******.\n           :          =%%%###%*##*##*#**-\n           ::        +%%%%%%%####*####***\n           -=       -%%%@@@%#%##%######**\n           ==       .%%%@@@%%%##%#%%**##*\n           ==.       %%%@%@%%%##%##%#*#**.\n           ==:       %%%@%@%%%##%#%@*###*+\n           ==:       %%%%@%%%%%%%%#%####*+\n           ==:      :%%%%%%*=-=+##%%#%%#*+\n           ===      .%%@%#*+=-::-::.+#***+\n           ===       %%%#**#*+-----+=*##*=\n           -==      .%%%#***##=-:-==-+%#*       .---:\n          .--=      -%%%%*+#+%#:.:+*-###*      -#=+===.\n          .---      %%%%%#===#*:.:==:*##*    :#%%##*++=-\n          :---     #@%%@@%%%%%%%#=-+####*    -%%%%%*#*=+=\n          ::--.   :%@%%@%%%%%%%%%##%%%%#*     :.:%%##%+**\n          :::-:   -@@%%@@@@@%%%%%%%##%###:.      +%#+=+*+\n          ::::-   #@@%%@@@@@@@%%%%%%*#####+++    =%%##=-:\n          ::::-   %@@%%@@@@@@@%%##%%#####%*%#*   =#%%#*+-\n          :::::  +%@@%%@@@@@@@%%%%%@####%@%####= %%%%%##+\n          :::::%@%%@@%%@@@@@%@@%%%#@%##*@@%#%%%%%%@@%#%*=\n          :::::%@%%@@%%@@@@@@%%%%%#%%%#%@@@%%%%%@@@@%%#**\n          :::::%%%@@%%%@@@@@@%%%%#%%%%#%@@@@#%%%@@@@@%*+=\n          --:::#%%@%#@%@@@@@@@%%#%%%#%#@@@@@%##%#%@@%*+=-\n         -#*+=.%%%##%%@%@@@@%%%%%%%%%#%@@@@@%*%@@%%@%*=*-\n        -**#*+*%%#%%%@@@@@@@@%@%%#%%#*@@@@@@#%#%@@%%%+++:\n       .**+*+###%*%%@@@%@@@@@%%%%%%**#%@@@@%@%*+@@@%%**%\n      .#%******+*%#%@@@@@@@@@%@%%%**#%%@@@@%@%**@##%#*=+:\n      *@%%#*+##+=###%%@@@@@@@%%##%**#%%@@@@@@@@@*#%%#++=:\n     =*##**##+%**#####%@@@@@%%%%@@*##%%@@@@@%@@##%%##+#+#\n     **###+=+**%*###**%@@@@@@%%@@##*#%%@@@@@@%@%@@@%##@-%+\n    +##%%#*+==+####****%@@@@%###%####%%@@@@@@@@%@@@@##@@#+\n    ###@@%%+*+*+*###***#@@%%%%##%#*##@%%@@@@@@@@@@@@%##*++\n    #%#%%%%##%***##*****@@@%##**####%%%@@@@@@@@@@@@@@%#**+\n    #%%#%##+==#%%%%#****%@@%####*###%##%@@@@@@@@@@@@%%%**+:\n    #%%%%###*++*#@@%*#**%@@@%#*#+######%@@@@@@@@@@@@%%##++:\n    =#%%%###**#*#@@@*#**#@@@###**#%####%@@@@@@@@@@@@@@#**+:\n    =%%%%#*==*%%%@@@*#*#*@@@%####%%####%@@@@@@@@@@@@@@#*++-\n    =%%###+==+*#%@@@***%#%@@%######*###%@@@@@@@@@@@@@@%*++-\n    #%@%###*####*@@@#**%##@@@%##*+####%%@@@@@@@@@@@@@@%*++-\n  .%@%@%##%*+*#%#@@@***%%*%@@%###*####%%%@@@@@@@@@@@@@%*++:\n  *#%@%%*%%+=++#+%@%#**@@*%@@%##%#####%%%@@@@@@@@@@@@@%*++:\n  @%%@@%%#%#%####%@%#**@@##@@%##%##%##%@%@@@@@@@@@%@@@%*+*-\n  @%%@@@@%#%#***#@@%#**@@##@@%##%##%###@%%@@@@@@@@%%@@%++*:\n  @%##@@@%%#**###@@%##*%@%*@@%#%%%%%##%%@%@@@@@@@@%%@@%+*#:\n  #%%#@@@@%***###@@%%###@@*%@#%%%%@@##%%@%%*%@@@@%@%@@%**#.\n  -@%@@%###*#*##@@@%%%##@@#%##@@%@@@@%%@@%- .@@@@%@%%@%***\n  =@@@@%%%######@@@%%@%#%@@%#%@@@@@@@@@@@%*  -@@@%%#%@%**:\n  %@@%@%#########@@%#%@@%%@%#%@%@%%@@@@@@@%   %@@@##%@%**\n  @@@@@%%####%##@@@@@%%%@%%%%@%##%%%@@@@@@%*  :#@@%##%##:\n .@@@@@%%##%###%@@@@@@@##%%%%#@%#*%@@@@@@@%*    %@@##%##\n *@@@@@%%###@#%%%%%%%%##%@%%%@@%#*##%@@@@@%+     =#%##+\n *@@@@@@%##%@#%@%%%%%###%%%@@@@%####%@@@%%+       .**+\n #@@@@@@%#%%%#%@%%%%%%#%%@@@@@@#####%%%%#+=-\n",
      "@damage": "5..10",
      "@armor": 1,
      "@max_health": 50,
      "@health": 50,
      "@inventory": "REF1440",
      "@dead": false
    },
    {
      "klass": "Enemy",
      "req_params": 4,
      "@id": 1460,
      "@name": "Boss",
      "@pos_x": 6,
      "@pos_y": 8,
      "@map_marker": "@",
      "@image": "                              -++++=\n                         :+#*********#:\n                        =#####**##*****+\n           .           =#%####**#*******.\n           :          =%%%###%*##*##*#**-\n           ::        +%%%%%%%####*####***\n           -=       -%%%@@@%#%##%######**\n           ==       .%%%@@@%%%##%#%%**##*\n           ==.       %%%@%@%%%##%##%#*#**.\n           ==:       %%%@%@%%%##%#%@*###*+\n           ==:       %%%%@%%%%%%%%#%####*+\n           ==:      :%%%%%%*=-=+##%%#%%#*+\n           ===      .%%@%#*+=-::-::.+#***+\n           ===       %%%#**#*+-----+=*##*=\n           -==      .%%%#***##=-:-==-+%#*       .---:\n          .--=      -%%%%*+#+%#:.:+*-###*      -#=+===.\n          .---      %%%%%#===#*:.:==:*##*    :#%%##*++=-\n          :---     #@%%@@%%%%%%%#=-+####*    -%%%%%*#*=+=\n          ::--.   :%@%%@%%%%%%%%%##%%%%#*     :.:%%##%+**\n          :::-:   -@@%%@@@@@%%%%%%%##%###:.      +%#+=+*+\n          ::::-   #@@%%@@@@@@@%%%%%%*#####+++    =%%##=-:\n          ::::-   %@@%%@@@@@@@%%##%%#####%*%#*   =#%%#*+-\n          :::::  +%@@%%@@@@@@@%%%%%@####%@%####= %%%%%##+\n          :::::%@%%@@%%@@@@@%@@%%%#@%##*@@%#%%%%%%@@%#%*=\n          :::::%@%%@@%%@@@@@@%%%%%#%%%#%@@@%%%%%@@@@%%#**\n          :::::%%%@@%%%@@@@@@%%%%#%%%%#%@@@@#%%%@@@@@%*+=\n          --:::#%%@%#@%@@@@@@@%%#%%%#%#@@@@@%##%#%@@%*+=-\n         -#*+=.%%%##%%@%@@@@%%%%%%%%%#%@@@@@%*%@@%%@%*=*-\n        -**#*+*%%#%%%@@@@@@@@%@%%#%%#*@@@@@@#%#%@@%%%+++:\n       .**+*+###%*%%@@@%@@@@@%%%%%%**#%@@@@%@%*+@@@%%**%\n      .#%******+*%#%@@@@@@@@@%@%%%**#%%@@@@%@%**@##%#*=+:\n      *@%%#*+##+=###%%@@@@@@@%%##%**#%%@@@@@@@@@*#%%#++=:\n     =*##**##+%**#####%@@@@@%%%%@@*##%%@@@@@%@@##%%##+#+#\n     **###+=+**%*###**%@@@@@@%%@@##*#%%@@@@@@%@%@@@%##@-%+\n    +##%%#*+==+####****%@@@@%###%####%%@@@@@@@@%@@@@##@@#+\n    ###@@%%+*+*+*###***#@@%%%%##%#*##@%%@@@@@@@@@@@@%##*++\n    #%#%%%%##%***##*****@@@%##**####%%%@@@@@@@@@@@@@@%#**+\n    #%%#%##+==#%%%%#****%@@%####*###%##%@@@@@@@@@@@@%%%**+:\n    #%%%%###*++*#@@%*#**%@@@%#*#+######%@@@@@@@@@@@@%%##++:\n    =#%%%###**#*#@@@*#**#@@@###**#%####%@@@@@@@@@@@@@@#**+:\n    =%%%%#*==*%%%@@@*#*#*@@@%####%%####%@@@@@@@@@@@@@@#*++-\n    =%%###+==+*#%@@@***%#%@@%######*###%@@@@@@@@@@@@@@%*++-\n    #%@%###*####*@@@#**%##@@@%##*+####%%@@@@@@@@@@@@@@%*++-\n  .%@%@%##%*+*#%#@@@***%%*%@@%###*####%%%@@@@@@@@@@@@@%*++:\n  *#%@%%*%%+=++#+%@%#**@@*%@@%##%#####%%%@@@@@@@@@@@@@%*++:\n  @%%@@%%#%#%####%@%#**@@##@@%##%##%##%@%@@@@@@@@@%@@@%*+*-\n  @%%@@@@%#%#***#@@%#**@@##@@%##%##%###@%%@@@@@@@@%%@@%++*:\n  @%##@@@%%#**###@@%##*%@%*@@%#%%%%%##%%@%@@@@@@@@%%@@%+*#:\n  #%%#@@@@%***###@@%%###@@*%@#%%%%@@##%%@%%*%@@@@%@%@@%**#.\n  -@%@@%###*#*##@@@%%%##@@#%##@@%@@@@%%@@%- .@@@@%@%%@%***\n  =@@@@%%%######@@@%%@%#%@@%#%@@@@@@@@@@@%*  -@@@%%#%@%**:\n  %@@%@%#########@@%#%@@%%@%#%@%@%%@@@@@@@%   %@@@##%@%**\n  @@@@@%%####%##@@@@@%%%@%%%%@%##%%%@@@@@@%*  :#@@%##%##:\n .@@@@@%%##%###%@@@@@@@##%%%%#@%#*%@@@@@@@%*    %@@##%##\n *@@@@@%%###@#%%%%%%%%##%@%%%@@%#*##%@@@@@%+     =#%##+\n *@@@@@@%##%@#%@%%%%%###%%%@@@@%####%@@@%%+       .**+\n #@@@@@@%#%%%#%@%%%%%%#%%@@@@@@#####%%%%#+=-\n",
      "@damage": "10..20",
      "@armor": 3,
      "@max_health": 200,
      "@health": 200,
      "@inventory": "REF1480",
      "@dead": false
    },
    {
      "klass": "Shop",
      "req_params": 1,
      "@id": 1500,
      "@name": "NPC name",
      "@pos_x": 6,
      "@pos_y": 5,
      "@map_marker": "$",
      "@image": "                               --=.  ....\n                              -::::.....:.\n                             --::.........\n                            =-::...........\n                           .--::...........\n                           ---::.............\n                          :--:::...... . ....\n                          ---::.......   .....\n                          ---::.....      .....\n                         :--:::......    .....::\n            . :          :--:::......    ....::-.\n           |   .        .-:-::......   .....::-==\n              ..:       .:--::............::--=+*.\n          .    .:.      .-=-::...........::-==+++- .........\n            .  .::.     -==-::.........::--==+++=...........\n           .    ::..    =+=-::.......:::--==+++ ............\n            .    :::   .#%%%#%*##*#+++**+=+++-..............\n             .   ..:...*####****#####%%%%%%#-..... .........\n                 ... =====-------=====++*%%.................\n               : ...::-===------------===-..:=-::::.........\n                :...::::-:-------------=.====+*#--:.........\n                 :...:=+==*:..:--:.:----=-===++*#=:.........\n                  ::.-+=-+*+++++====-========+**#+:.........\n                   ::=++-*++==++=====++++++==+****:.........\n                     ==+=+***:=*+=--+*#=-=+===**##=:........\n                     -++=+*+==+**====+*-=+====***+=:........\n                     :*=++====+**====+=--==-==**+==-........\n                     .*-++===++**=======-====+**=-+:......\n                      +-=+===+***====-===-===+*++==:.....\n                      =-=+===+**+====---=-==+=*==+=....\n                      ===+===***=====-=---===++-++=..\n                      =+++===***=-===-=---====++==\n                      .=++==++**+====--=--===+=--:\n                       -+==+***+======-=-====+=--.\n                       =++=+**+===--=========+--.\n                       -+==+**-*=====-*=======\n                       -+=+++*++=----========:\n                      -===+++*++==-==--======\n                     .*%=+++++++=====--=====-\n                     :*%+++++*++==--========\n                     -=%+++=+++=====+======:\n                    ::=**++++++==-=========\n                    ::==**++++============-\n                   :-----**+++=====-=====+\n                  ---:----*+++=+===+====+=\n               .:.==-::--:=++++++======++=:\n             :-:..=--::--::-=++++=====+++=:.\n           :=--:::=---:--::.-==++=======+=:.\n        .----:::::-+---:-::..==+++======*=:.-..\n      -::.:----:..:-:--.::.. :===+++===+*=:::::-\n   :--::....::::::::=::..:..:=:========+#=-::::-::.\n.:-=---:::::...:::-:=::...:-:-=-=======+#=--::-===::\n---::::::--.:....=+:+:....-:::-::======+++=--.=-----:.\n--:::::-::=*:....:-:+:...::...::-:====+*+==-:+=--::-::-\n:-:.::.=+::+*:....::=-:::::....:-:-===+*=--::-*-:::=----\n-::::.::=+==#+...::..::::::....::::==+*+=---::=+-::-----:\n:.::..::.-=*=-==-... .::..:::...:::-=+*=---::::=-::*=-=-::\n:..:::::.....:::--.  :....::.....::.=*+--::::::.:::*-:+:::\n::...::::....-:::::.-:.....:........:#-::::::.:::----=-.::.\n:-:...-:::...::..:::::.....:....... :=:-::-::.:-::-:--:.::.\n.-::..:.::.:.......::::....::...... .:::::-:::::-:-::=..::.\n.-::..::::::::. .. :.::.....::.....:--::.:-::::::::::-:.:-:.\n:::..::::::...:::..:::::...::::.:.::=-::::-::::::::::::::-::\n.::....:.::...::::::.::-:::.:::....:+-.-::---:::--:.::--:::.\n..:....-::-:::::::....::.....::....:+::...:::::::--::-:::::.\n",
      "@inventory": "REF1520",
      "@greeting": "Welcome to the shop!",
      "@goodbye": "Come back again soon!"
    },
    {
      "klass": "QuestGiver",
      "req_params": 0,
      "@id": 1540,
      "@name": "NPC name",
      "@pos_x": 6,
      "@pos_y": 9,
      "@map_marker": "?",
      "@image": "                           ....\n                         .:=--::....\n                       .:----:--::.:.\n                      .--==---=--:.:-:.\n                     .:---=--=-=-::-+=-.\n                    .:-=--=------:-=+---\n                    .====-=-==-=----=-::-\n                   .:=-====-=-====----:...\n                   .-----==-======--:::. .\n                   .--:------=-====-:::\n                   :--:------======-:-:.\n                   :=--------====+=-::::\n                   ------------====-::-::\n                  .-=--=-------==++=:..:-:\n                  .-:-+=------=####+..:-::-\n                  .=:*###++==+##*++=:.:=:.--\n                  .-:=++##*==**++++=-..=:.-+:\n                  .-:+*##++=+*=*+%#+-..=+:.+-\n                  :---=+=====*+==+=-=. -**.+-\n                  ::----=---==+=-==--: :**:=:\n                  ::---==-:=-:+=-==--:.:+*.+:\n                  :-------:==.-=--===-::-+.+.\n                  :--==---:==.-+-====-:::=.=.\n                  .:----=---=-:----==-::-:::\n                  .:--:-====+##*=-:---:::.:.\n                  .:::--=-=+#*+=--::=-:.-.:.\n                 ..::::-::====-::-::--:.:.:.\n                 ..::::.:-=-==-:.:::-:.:..:.\n                 ..:::.:-++***+-...:.:....:.\n                 ...::.:====++==....:.....: .\n                 ...:..:========-:........:\n                 .:..:::=---=-----:.:.....-:\n                 .::.:.:---==----::.......:-.\n                 .::::::---===----:....:=..::\n                 .:::::.:--===:::::...::--::::....\n                 .:::::..::-=--:::...::--:.:::::::..\n                 .::::::::::---::::..:--:.....::....\n                ..:-:.::::-----:-:::--=:::::.....\n                 .:-:::::::----:::::--:.............\n                 .:-:::::::----:::::::....:--::::... :.\n             .  ..:=-::-:::---::-:----::..::::.::...   .\n         .:::.. ..-*=::-:::---:----::::...::........... .\n         .:...  ..-=:--::::--:--==-:.:...........:::....\n         .: .. . .+=====:::-----::.......:--:.:.:::::::..\n         ....  ..:--%=--:=---::--.::-:::.:.:..::::::.::::.\n        ..  . ...:::#*-:==---::::..............::.::. .:::.\n        :.  .....:.-*+++*=::::..........::::.. .....:. :-::\n       :.....:..:-.::::=+..... ... . . ....... .....:. .:::.\n      .:.  ..:..::.-:...... . ....    ........ .....:: .:::.\n      ::   ..:..:.:::..  .    ... . .......... .....::..:--.\n      --  ...:..::::......     . .      .. ... .....:-...:-.\n     .-: ....:...:-......    ....      ......  ..:..:=:  .:.\n     .= . .......::..... .    .  .     ....    .....:-:  .-.\n     .+ . ..:....=:......   ..  ...     ..    .....::::  .:-\n    ..- ........-::.....    ...  .       .   ......::::. ..=\n   .... ........=::....   ...            .   ......::...  :-\n  ..... . .....:#-.....  ... .       .        .....:....  .-\n ....:. . .....:-:....   ..            .  ..............   :\n ....:... .....-.....   ....             ... .....:.....   -\n.:...::  .. ...*:.. .. ... ...     .   .    .............  -\n.:. .-:.  ....:+:....  .. ...       .    .  .............  .\n.:...:-.  ....:-....   .... .   .      ... ..............\n::...:=.  ....--...   .... .   .       .:. ..:...:......:.\n-:...:-.. ....--.... . .  .      .  . ..:  ......:......:. .\n::...:=.   . .--. ..  .. ..      .. ...:. ......::........\n",
      "@quests": ["REF1280", "REF1300", "REF1320"],
      "@greeting": "Hello there!",
      "@goodbye": "Goodbye!"
    }
  ],
  "weapons": [
    {
      "klass": "Weapon",
      "req_params": 8,
      "@id": 1140,
      "@name": "Sword",
      "@description": "Basic sword",
      "@price": 100,
      "@stackable": false,
      "@stack_count": 1,
      "@rarity": "Common",
      "@damage": "10..15",
      "@req_lvl": 1
    },
    {
      "klass": "Weapon",
      "req_params": 8,
      "@id": 1160,
      "@name": "Dagger",
      "@description": "Basic dagger",
      "@price": 150,
      "@stackable": false,
      "@stack_count": 1,
      "@rarity": "Common",
      "@damage": "12..16",
      "@req_lvl": 1
    },
    {
      "klass": "Weapon",
      "req_params": 8,
      "@id": 1180,
      "@name": "Mace",
      "@description": "Basic mace",
      "@price": 250,
      "@stackable": false,
      "@stack_count": 1,
      "@rarity": "Common",
      "@damage": "13..20",
      "@req_lvl": 1
    }
  ],
  "consumables": [
    {
      "klass": "Consumable",
      "req_params": 9,
      "@id": 1200,
      "@name": "Health Potion",
      "@description": "Restores 20 health points",
      "@price": 25,
      "@stackable": true,
      "@stack_count": 10,
      "@rarity": "Common",
      "@type": "+",
      "@amount": 20,
      "@attribute": "health"
    },
    {
      "klass": "Consumable",
      "req_params": 9,
      "@id": 1220,
      "@name": "Damage boost potion",
      "@description": "Doubles your damage",
      "@price": 40,
      "@stackable": true,
      "@stack_count": 5,
      "@rarity": "Common",
      "@type": "*",
      "@amount": 2,
      "@attribute": "damage"
    }
  ],
  "abilities": [
    {
      "klass": "Ability",
      "req_params": 3,
      "@id": 1240,
      "@name": "Attack",
      "@description": "Basic attack",
      "@target": "other",
      "@sign": "-",
      "@amount": "rand(@owner.damage)",
      "@attribute": "health",
      "@mana_cost": 0,
      "@owner": "REF1360",
      "@message": ""
    },
    {
      "klass": "Ability",
      "req_params": 3,
      "@id": 1260,
      "@name": "Heal",
      "@description": "Heals for 30 HP",
      "@target": "self",
      "@sign": "+",
      "@amount": "30",
      "@attribute": "health",
      "@mana_cost": 30,
      "@owner": "REF1360",
      "@message": "Player healed for 30 HP"
    }
  ],
  "quests": [
    {
      "klass": "Quest",
      "req_params": 3,
      "@id": 1280,
      "@name": "Getting started",
      "@description": "Kill an enemy!",
      "@conditions": ["Enemy.deaths > @starting[:enemy_deaths]"],
      "@xp_reward": 100,
      "@gold_reward": 100,
      "@item_reward": [],
      "@owner": null,
      "@starting": { "enemy_deaths": 0, "level": 0 }
    },
    {
      "klass": "Quest",
      "req_params": 3,
      "@id": 1300,
      "@name": "More = Better",
      "@description": "Level up!",
      "@conditions": ["@owner.level > @starting[:level]"],
      "@xp_reward": 0,
      "@gold_reward": 200,
      "@item_reward": ["REF1160"],
      "@owner": null,
      "@starting": { "enemy_deaths": 0, "level": 0 }
    },
    {
      "klass": "Quest",
      "req_params": 3,
      "@id": 1320,
      "@name": "Getting even higher",
      "@description": "Reach level 5",
      "@conditions": ["@owner.level > 5"],
      "@xp_reward": 0,
      "@gold_reward": 500,
      "@item_reward": [],
      "@owner": null,
      "@starting": { "enemy_deaths": 0, "level": 0 }
    }
  ],
  "map": {
    "klass": "Map",
    "req_params": 0,
    "@id": 1340,
    "@name": "Mapa",
    "@width": 25,
    "@height": 25,
    "@objects": ["REF1420", "REF1460", "REF1500", "REF1540", "REF1360"],
    "@out": [
      [
        "□",
        "□",
        "□",
        "□",
        "□",
        "□",
        "□",
        "□",
        "□",
        "□",
        "□",
        "□",
        "□",
        "□",
        "□",
        "□",
        "□",
        "□",
        "□",
        "□",
        "□",
        "□",
        "□",
        "□",
        "□"
      ],
      [
        "□",
        "□",
        "□",
        "□",
        "□",
        "□",
        "□",
        "□",
        "□",
        "□",
        "□",
        "□",
        "□",
        "□",
        "□",
        "□",
        "□",
        "□",
        "□",
        "□",
        "□",
        "□",
        "□",
        "□",
        "□"
      ],
      [
        "□",
        "□",
        "□",
        "□",
        "□",
        "□",
        "□",
        "□",
        "□",
        "□",
        "□",
        "□",
        "□",
        "□",
        "□",
        "□",
        "□",
        "□",
        "□",
        "□",
        "□",
        "□",
        "□",
        "□",
        "□"
      ],
      [
        "□",
        "□",
        "□",
        "□",
        "□",
        "□",
        "□",
        "□",
        "□",
        "□",
        "□",
        "□",
        "□",
        "□",
        "□",
        "□",
        "□",
        "□",
        "□",
        "□",
        "□",
        "□",
        "□",
        "□",
        "□"
      ],
      [
        "□",
        "□",
        "□",
        "□",
        "□",
        "□",
        "□",
        "□",
        "□",
        "□",
        "□",
        "□",
        "□",
        "□",
        "□",
        "□",
        "□",
        "□",
        "□",
        "□",
        "□",
        "□",
        "□",
        "□",
        "□"
      ],
      [
        "□",
        "□",
        "□",
        "□",
        "□",
        "□",
        "□",
        "□",
        "□",
        "□",
        "□",
        "□",
        "□",
        "□",
        "□",
        "□",
        "□",
        "□",
        "□",
        "□",
        "□",
        "□",
        "□",
        "□",
        "□"
      ],
      [
        "□",
        "□",
        "□",
        "□",
        "□",
        "□",
        "□",
        "□",
        "□",
        "□",
        "□",
        "□",
        "□",
        "□",
        "□",
        "□",
        "□",
        "□",
        "□",
        "□",
        "□",
        "□",
        "□",
        "□",
        "□"
      ],
      [
        "□",
        "□",
        "□",
        "□",
        "□",
        "□",
        "□",
        "□",
        "□",
        "□",
        "□",
        "□",
        "□",
        "□",
        "□",
        "□",
        "□",
        "□",
        "□",
        "□",
        "□",
        "□",
        "□",
        "□",
        "□"
      ],
      [
        "□",
        "□",
        "□",
        "□",
        "□",
        "□",
        "□",
        "□",
        "□",
        "□",
        "□",
        "□",
        "□",
        "□",
        "□",
        "□",
        "□",
        "□",
        "□",
        "□",
        "□",
        "□",
        "□",
        "□",
        "□"
      ],
      [
        "□",
        "□",
        "□",
        "□",
        "□",
        "□",
        "□",
        "□",
        "□",
        "□",
        "□",
        "□",
        "□",
        "□",
        "□",
        "□",
        "□",
        "□",
        "□",
        "□",
        "□",
        "□",
        "□",
        "□",
        "□"
      ],
      [
        "□",
        "□",
        "□",
        "□",
        "□",
        "□",
        "□",
        "□",
        "□",
        "□",
        "□",
        "□",
        "□",
        "□",
        "□",
        "□",
        "□",
        "□",
        "□",
        "□",
        "□",
        "□",
        "□",
        "□",
        "□"
      ],
      [
        "□",
        "□",
        "□",
        "□",
        "□",
        "□",
        "□",
        "□",
        "□",
        "□",
        "□",
        "□",
        "□",
        "□",
        "□",
        "□",
        "□",
        "□",
        "□",
        "□",
        "□",
        "□",
        "□",
        "□",
        "□"
      ],
      [
        "□",
        "□",
        "□",
        "□",
        "□",
        "□",
        "□",
        "□",
        "□",
        "□",
        "□",
        "□",
        "□",
        "□",
        "□",
        "□",
        "□",
        "□",
        "□",
        "□",
        "□",
        "□",
        "□",
        "□",
        "□"
      ],
      [
        "□",
        "□",
        "□",
        "□",
        "□",
        "□",
        "□",
        "□",
        "□",
        "□",
        "□",
        "□",
        "□",
        "□",
        "□",
        "□",
        "□",
        "□",
        "□",
        "□",
        "□",
        "□",
        "□",
        "□",
        "□"
      ],
      [
        "□",
        "□",
        "□",
        "□",
        "□",
        "□",
        "□",
        "□",
        "□",
        "□",
        "□",
        "□",
        "□",
        "□",
        "□",
        "□",
        "□",
        "□",
        "□",
        "□",
        "□",
        "□",
        "□",
        "□",
        "□"
      ],
      [
        "□",
        "□",
        "□",
        "□",
        "□",
        "□",
        "□",
        "□",
        "□",
        "□",
        "□",
        "□",
        "□",
        "□",
        "□",
        "□",
        "□",
        "□",
        "□",
        "□",
        "□",
        "□",
        "□",
        "□",
        "□"
      ],
      [
        "□",
        "□",
        "□",
        "□",
        "□",
        "□",
        "□",
        "□",
        "□",
        "□",
        "□",
        "□",
        "□",
        "□",
        "□",
        "□",
        "□",
        "□",
        "□",
        "□",
        "□",
        "□",
        "□",
        "□",
        "□"
      ],
      [
        "□",
        "□",
        "□",
        "□",
        "□",
        "□",
        "□",
        "□",
        "□",
        "□",
        "□",
        "□",
        "□",
        "□",
        "□",
        "□",
        "□",
        "□",
        "□",
        "□",
        "□",
        "□",
        "□",
        "□",
        "□"
      ],
      [
        "□",
        "□",
        "□",
        "□",
        "□",
        "□",
        "□",
        "□",
        "□",
        "□",
        "□",
        "□",
        "□",
        "□",
        "□",
        "□",
        "□",
        "□",
        "□",
        "□",
        "□",
        "□",
        "□",
        "□",
        "□"
      ],
      [
        "□",
        "□",
        "□",
        "□",
        "□",
        "□",
        "□",
        "□",
        "□",
        "□",
        "□",
        "□",
        "□",
        "□",
        "□",
        "□",
        "□",
        "□",
        "□",
        "□",
        "□",
        "□",
        "□",
        "□",
        "□"
      ],
      [
        "□",
        "□",
        "□",
        "□",
        "□",
        "□",
        "□",
        "□",
        "□",
        "□",
        "□",
        "□",
        "□",
        "□",
        "□",
        "□",
        "□",
        "□",
        "□",
        "□",
        "□",
        "□",
        "□",
        "□",
        "□"
      ],
      [
        "□",
        "□",
        "□",
        "□",
        "□",
        "□",
        "□",
        "□",
        "□",
        "□",
        "□",
        "□",
        "□",
        "□",
        "□",
        "□",
        "□",
        "□",
        "□",
        "□",
        "□",
        "□",
        "□",
        "□",
        "□"
      ],
      [
        "□",
        "□",
        "□",
        "□",
        "□",
        "□",
        "□",
        "□",
        "□",
        "□",
        "□",
        "□",
        "□",
        "□",
        "□",
        "□",
        "□",
        "□",
        "□",
        "□",
        "□",
        "□",
        "□",
        "□",
        "□"
      ],
      [
        "□",
        "□",
        "□",
        "□",
        "□",
        "□",
        "□",
        "□",
        "□",
        "□",
        "□",
        "□",
        "□",
        "□",
        "□",
        "□",
        "□",
        "□",
        "□",
        "□",
        "□",
        "□",
        "□",
        "□",
        "□"
      ],
      [
        "□",
        "□",
        "□",
        "□",
        "□",
        "□",
        "□",
        "□",
        "□",
        "□",
        "□",
        "□",
        "□",
        "□",
        "□",
        "□",
        "□",
        "□",
        "□",
        "□",
        "□",
        "□",
        "□",
        "□",
        "□"
      ]
    ]
  },
  "inventories": [
    {
      "klass": "Inventory",
      "req_params": 1,
      "@id": 1380,
      "@items": ["REF1140", "REF1200", "REF1200", "REF1200"],
      "@max_slots": 10
    },
    {
      "klass": "Inventory",
      "req_params": 1,
      "@id": 1440,
      "@items": [],
      "@max_slots": 5
    },
    {
      "klass": "Inventory",
      "req_params": 1,
      "@id": 1480,
      "@items": [],
      "@max_slots": 5
    },
    {
      "klass": "Inventory",
      "req_params": 1,
      "@id": 1520,
      "@items": ["REF1160", "REF1180", "REF1200", "REF1220"],
      "@max_slots": 10
    }
  ]
}
